{"page":9,"width":1305,"height":1826,"lines":[{"text":"Bi RE AE","confidence":48.7,"x":0.51571,"y":0.26287,"width":0.10268,"height":0.00767},{"text":"FS","confidence":69.4,"x":0.5433,"y":0.27273,"width":0.01992,"height":0.00767},{"text":"ga ae we we","confidence":54.6,"x":0.51571,"y":0.28204,"width":0.10268,"height":0.00821},{"text":"TI","confidence":42.5,"x":0.32107,"y":0.35268,"width":0.02069,"height":0.00602},{"text":"LI","confidence":63.8,"x":0.96398,"y":0.35323,"width":0.01916,"height":0.00548},{"text":"e.","confidence":52.9,"x":0.41762,"y":0.35816,"width":0.09195,"height":0.03724},{"text":"rt","confidence":51.3,"x":0.25824,"y":0.41128,"width":0.02069,"height":0.00548},{"text":"rr","confidence":44.5,"x":0.32107,"y":0.41128,"width":0.02069,"height":0.00548},{"text":"Hi, su Hai.) Ha I","confidence":76.0,"x":0.57701,"y":0.41347,"width":0.25747,"height":0.046},{"text":"Liu Tao.","confidence":85.4,"x":0.77088,"y":0.4655,"width":0.09042,"height":0.0345},{"text":"Ws,","confidence":42.4,"x":0.43908,"y":0.569,"width":0.05517,"height":0.04272},{"text":"Good morning","confidence":96.5,"x":0.57011,"y":0.70591,"width":0.17471,"height":0.01807},{"text":"Good morning","confidence":96.8,"x":0.57011,"y":0.73494,"width":0.17471,"height":0.01807},{"text":"Good morning","confidence":95.7,"x":0.57011,"y":0.76396,"width":0.17471,"height":0.01862},{"text":"Morning, my teacher","confidence":96.6,"x":0.57165,"y":0.79354,"width":0.25594,"height":0.01807},{"text":"Good morning","confidence":95.9,"x":0.57011,"y":0.83352,"width":0.17471,"height":0.01862},{"text":"Good morning","confidence":96.7,"x":0.57011,"y":0.86309,"width":0.17471,"height":0.01807},{"text":"Good morning","confidence":96.2,"x":0.57011,"y":0.89211,"width":0.17471,"height":0.01862},{"text":"Morning, my friend","confidence":96.4,"x":0.57165,"y":0.92114,"width":0.23525,"height":0.01862}]}