{"page":59,"width":1305,"height":1826,"lines":[{"text":"SIX","confidence":81.2,"x":0.70651,"y":0.16156,"width":0.02912,"height":0.01041},{"text":"five","confidence":96.6,"x":0.58774,"y":0.17634,"width":0.04368,"height":0.01533},{"text":"one","confidence":96.5,"x":0.56398,"y":0.27108,"width":0.04444,"height":0.01095},{"text":"two","confidence":96.3,"x":0.86207,"y":0.29135,"width":0.04674,"height":0.01314},{"text":"LES","confidence":81.3,"x":0.16628,"y":0.38664,"width":0.03295,"height":0.0115},{"text":"Se","confidence":47.7,"x":0.24368,"y":0.44195,"width":0.0751,"height":0.01041},{"text":"three","confidence":97.0,"x":0.39157,"y":0.4989,"width":0.06437,"height":0.01643},{"text":"How old are you?","confidence":96.8,"x":0.6069,"y":0.69222,"width":0.21533,"height":0.01862},{"text":"I'm nine today!","confidence":95.0,"x":0.60613,"y":0.7218,"width":0.18467,"height":0.01807},{"text":"Come to my partu.","confidence":93.4,"x":0.60613,"y":0.75192,"width":0.22529,"height":0.01752},{"text":"It's time to play!","confidence":92.0,"x":0.60613,"y":0.78039,"width":0.1977,"height":0.01807},{"text":"ann","confidence":42.7,"x":0.04828,"y":0.96057,"width":0.03295,"height":0.00712}]}