{"page":39,"width":1305,"height":1826,"lines":[{"text":"ee","confidence":44.5,"x":0.86054,"y":0.0,"width":0.13716,"height":0.05093},{"text":"A Match and say","confidence":95.2,"x":0.09425,"y":0.10515,"width":0.22605,"height":0.02136},{"text":"Ges","confidence":45.9,"x":0.69502,"y":0.2667,"width":0.03678,"height":0.00931},{"text":"fis et Toe","confidence":54.7,"x":0.39234,"y":0.44469,"width":0.2,"height":0.05531},{"text":"B Act it out","confidence":94.5,"x":0.09655,"y":0.57065,"width":0.15556,"height":0.02574},{"text":"In groups, take turns introducing the other students.","confidence":96.3,"x":0.09732,"y":0.60953,"width":0.58927,"height":0.01698},{"text":"C Make and say","confidence":94.5,"x":0.09502,"y":0.67141,"width":0.21379,"height":0.02136},{"text":"Who are your friends? Make a card about them. Then introduce them","confidence":96.3,"x":0.09502,"y":0.70701,"width":0.79387,"height":0.01752},{"text":"to the class.","confidence":96.4,"x":0.09502,"y":0.73111,"width":0.1364,"height":0.01369},{"text":"I This","confidence":94.9,"x":0.24904,"y":0.75739,"width":0.07586,"height":0.03395},{"text":"She's my friend.","confidence":94.2,"x":0.27893,"y":0.79518,"width":0.19234,"height":0.01862},{"text":"This is","confidence":86.1,"x":0.27816,"y":0.81928,"width":0.07126,"height":0.01479},{"text":"He's my friend too.","confidence":91.9,"x":0.28046,"y":0.84283,"width":0.22989,"height":0.01862}]}