{"page":88,"width":1305,"height":1826,"lines":[{"text":"ja id","confidence":83.7,"x":0.45517,"y":0.09255,"width":0.10651,"height":0.04053},{"text":"ARE (LS","confidence":46.5,"x":0.3272,"y":0.19222,"width":0.14406,"height":0.01752},{"text":"LI","confidence":44.1,"x":0.79923,"y":0.26725,"width":0.05747,"height":0.01698},{"text":"(a","confidence":43.9,"x":0.22375,"y":0.30011,"width":0.01149,"height":0.00986},{"text":"IN","confidence":59.3,"x":0.22069,"y":0.30997,"width":0.01609,"height":0.00602},{"text":"BATTS, SH A","confidence":51.5,"x":0.21303,"y":0.32913,"width":0.64291,"height":0.02683},{"text":"beth TAH SE, BUM EBON","confidence":55.5,"x":0.15939,"y":0.3609,"width":0.50498,"height":0.02738},{"text":"HS BAB SA","confidence":57.2,"x":0.16092,"y":0.39485,"width":0.69502,"height":0.01698},{"text":"Pat.","confidence":49.3,"x":0.56245,"y":0.46769,"width":0.0613,"height":0.02738},{"text":"ASA","confidence":50.1,"x":0.76245,"y":0.50164,"width":0.09349,"height":0.01752},{"text":"ABM, APA Bite","confidence":47.9,"x":0.39387,"y":0.57448,"width":0.46284,"height":0.02738},{"text":"HIS","confidence":42.5,"x":0.16092,"y":0.60624,"width":0.04215,"height":0.02738},{"text":"BUF jiaocaiyilin.com","confidence":65.8,"x":0.21226,"y":0.68346,"width":0.32644,"height":0.02026},{"text":"LS ARE","confidence":54.0,"x":0.66054,"y":0.7448,"width":0.07969,"height":0.02793},{"text":"(LSA","confidence":44.4,"x":0.48659,"y":0.7793,"width":0.10651,"height":0.01698},{"text":"oa Al","confidence":45.9,"x":0.78238,"y":0.8724,"width":0.07739,"height":0.02738}]}