{"page":54,"width":1305,"height":1826,"lines":[{"text":"ee","confidence":45.9,"x":0.0,"y":0.0,"width":0.8,"height":0.09529},{"text":"A Read and complete","confidence":93.5,"x":0.11034,"y":0.10515,"width":0.28506,"height":0.02136},{"text":"cloudy","confidence":95.8,"x":0.24981,"y":0.15279,"width":0.07969,"height":0.01807},{"text":"rainy","confidence":96.7,"x":0.4636,"y":0.15279,"width":0.06054,"height":0.01807},{"text":"sunny","confidence":96.6,"x":0.65747,"y":0.15663,"width":0.0705,"height":0.01424},{"text":"On Friday, it is","confidence":96.3,"x":0.17011,"y":0.19332,"width":0.17548,"height":0.01807},{"text":"On Saturday, it is","confidence":96.1,"x":0.17011,"y":0.2207,"width":0.20996,"height":0.01862},{"text":"On Sunday, it is","confidence":95.5,"x":0.17011,"y":0.24863,"width":0.19004,"height":0.01862},{"text":"B Read and answer","confidence":95.5,"x":0.11264,"y":0.30066,"width":0.2567,"height":0.01752},{"text":"I Why is Bobby happy on Sunday?","confidence":93.0,"x":0.11418,"y":0.3368,"width":0.40766,"height":0.01862},{"text":"Why does Bobby's father say save your money for a rainy day?","confidence":94.8,"x":0.141,"y":0.36966,"width":0.7433,"height":0.01752},{"text":"C Draw and say","confidence":95.6,"x":0.11111,"y":0.40635,"width":0.21226,"height":0.02136},{"text":"Draw the weather today. Say what you can do in this weather.","confidence":96.1,"x":0.11264,"y":0.4414,"width":0.70498,"height":0.01752},{"text":"Draw a picture here!","confidence":96.2,"x":0.24215,"y":0.46769,"width":0.21303,"height":0.02629},{"text":"today","confidence":96.9,"x":0.65287,"y":0.48576,"width":0.0705,"height":0.01807},{"text":"We can","confidence":94.3,"x":0.58391,"y":0.51588,"width":0.08889,"height":0.01369},{"text":"ti","confidence":43.1,"x":0.17471,"y":0.62048,"width":0.00766,"height":0.00657},{"text":"Listen to the sentence from the story and read. be","confidence":93.0,"x":0.14406,"y":0.64513,"width":0.59464,"height":0.04272},{"text":"I want a red toy car.","confidence":93.4,"x":0.1433,"y":0.69222,"width":0.24751,"height":0.01807},{"text":"Listen to the rhyme and chant along. Then find more words. bo","confidence":93.2,"x":0.14406,"y":0.71084,"width":0.74713,"height":0.04272},{"text":"ca","confidence":45.3,"x":0.59387,"y":0.77273,"width":0.05441,"height":0.01205},{"text":"It's Wednesday today","confidence":94.0,"x":0.1433,"y":0.78204,"width":0.26437,"height":0.01862},{"text":"With cold wet weather.","confidence":96.0,"x":0.14253,"y":0.81106,"width":0.28506,"height":0.01479},{"text":"Wednesday","confidence":93.9,"x":0.73716,"y":0.81544,"width":0.14253,"height":0.01807},{"text":"Bw","confidence":50.6,"x":0.62452,"y":0.83187,"width":0.03755,"height":0.01643},{"text":"Let's stay inside","confidence":94.8,"x":0.14483,"y":0.84064,"width":0.18851,"height":0.01807},{"text":"And read together!","confidence":96.8,"x":0.14253,"y":0.86966,"width":0.23448,"height":0.01807}]}