{"page":32,"width":1197,"height":1676,"lines":[{"text":"Grammar time","confidence":96.3,"x":0.20802,"y":0.08473,"width":0.25815,"height":0.0537},{"text":"two fish","confidence":96.9,"x":0.32247,"y":0.17005,"width":0.09691,"height":0.01492},{"text":"We","confidence":96.7,"x":0.12364,"y":0.20346,"width":0.03926,"height":0.01372},{"text":"a rabbit","confidence":92.5,"x":0.32331,"y":0.21897,"width":0.09691,"height":0.01492},{"text":"have","confidence":96.5,"x":0.22473,"y":0.22076,"width":0.05681,"height":0.01492},{"text":"You","confidence":96.7,"x":0.12364,"y":0.24045,"width":0.04762,"height":0.01372},{"text":"a parrot","confidence":84.6,"x":0.32331,"y":0.27088,"width":0.10025,"height":0.01671},{"text":"They","confidence":96.7,"x":0.12364,"y":0.27685,"width":0.05848,"height":0.0185},{"text":"He","confidence":96.5,"x":0.12615,"y":0.31683,"width":0.02924,"height":0.01372},{"text":"She","confidence":96.6,"x":0.12448,"y":0.35501,"width":0.04177,"height":0.01492},{"text":"has","confidence":97.0,"x":0.22473,"y":0.35501,"width":0.03926,"height":0.01492},{"text":"a bird","confidence":92.9,"x":0.32331,"y":0.35501,"width":0.07018,"height":0.01492},{"text":"two legs","confidence":96.8,"x":0.32247,"y":0.39499,"width":0.10192,"height":0.0185},{"text":"It","confidence":96.8,"x":0.12448,"y":0.39618,"width":0.01587,"height":0.01372},{"text":"have has","confidence":94.5,"x":0.13952,"y":0.46002,"width":0.1721,"height":0.01492},{"text":"you","confidence":97.0,"x":0.21805,"y":0.52983,"width":0.04428,"height":0.01372},{"text":"Do","confidence":96.9,"x":0.12531,"y":0.54833,"width":0.03175,"height":0.01372},{"text":"they","confidence":96.5,"x":0.21637,"y":0.56981,"width":0.0543,"height":0.0185},{"text":"have","confidence":96.2,"x":0.31495,"y":0.59189,"width":0.05597,"height":0.01492},{"text":"an animal friend","confidence":96.1,"x":0.40769,"y":0.59189,"width":0.20217,"height":0.01492},{"text":"he","confidence":97.0,"x":0.21805,"y":0.61396,"width":0.02757,"height":0.01492},{"text":"Does","confidence":96.8,"x":0.12531,"y":0.63723,"width":0.05681,"height":0.01372},{"text":"she","confidence":97.0,"x":0.21721,"y":0.65871,"width":0.03843,"height":0.01492},{"text":"he","confidence":97.0,"x":0.57477,"y":0.71838,"width":0.02757,"height":0.01492},{"text":"does","confidence":96.9,"x":0.64996,"y":0.71838,"width":0.05514,"height":0.01492},{"text":"Yes","confidence":96.8,"x":0.46784,"y":0.71957,"width":0.04094,"height":0.01372},{"text":"do","confidence":96.9,"x":0.3066,"y":0.72792,"width":0.03008,"height":0.01492},{"text":"Yes","confidence":95.9,"x":0.12448,"y":0.72912,"width":0.0401,"height":0.01372},{"text":"we","confidence":96.8,"x":0.22891,"y":0.76611,"width":0.03509,"height":0.01074},{"text":"she","confidence":97.0,"x":0.5731,"y":0.7679,"width":0.03843,"height":0.01492},{"text":"doesn't","confidence":64.4,"x":0.64996,"y":0.7679,"width":0.08855,"height":0.01492},{"text":"No","confidence":96.7,"x":0.46951,"y":0.76909,"width":0.03175,"height":0.01372},{"text":"don't","confidence":91.8,"x":0.3066,"y":0.79594,"width":0.06349,"height":0.01492},{"text":"No","confidence":96.1,"x":0.12531,"y":0.79714,"width":0.03175,"height":0.01372},{"text":"they","confidence":96.5,"x":0.22891,"y":0.80728,"width":0.0543,"height":0.0185},{"text":"don't do not","confidence":82.4,"x":0.15038,"y":0.85263,"width":0.1746,"height":0.01492},{"text":"doesn't does not","confidence":95.8,"x":0.15038,"y":0.88783,"width":0.22306,"height":0.01492}]}